trunk_yls/__init__.py
trunk_yls/__main__.py
trunk_yls/yls_check.py
trunk_yls-1.0.2.dist-info/LICENSE
trunk_yls-1.0.2.dist-info/METADATA
trunk_yls-1.0.2.dist-info/WHEEL
trunk_yls-1.0.2.dist-info/entry_points.txt
trunk_yls-1.0.2.dist-info/top_level.txt
trunk_yls-1.0.2.dist-info/RECORD
